hackagent/__init__.py
hackagent/agent.py
hackagent/client.py
hackagent/errors.py
hackagent/logger.py
hackagent/types.py
hackagent/utils.py
hackagent/api/__init__.py
hackagent/api/agent/__init__.py
hackagent/api/agent/agent_create.py
hackagent/api/agent/agent_destroy.py
hackagent/api/agent/agent_list.py
hackagent/api/agent/agent_partial_update.py
hackagent/api/agent/agent_retrieve.py
hackagent/api/agent/agent_update.py
hackagent/api/apilogs/__init__.py
hackagent/api/apilogs/apilogs_list.py
hackagent/api/apilogs/apilogs_retrieve.py
hackagent/api/attack/__init__.py
hackagent/api/attack/attack_create.py
hackagent/api/attack/attack_destroy.py
hackagent/api/attack/attack_list.py
hackagent/api/attack/attack_partial_update.py
hackagent/api/attack/attack_retrieve.py
hackagent/api/attack/attack_update.py
hackagent/api/checkout/__init__.py
hackagent/api/checkout/checkout_create.py
hackagent/api/generate/__init__.py
hackagent/api/generate/generate_create.py
hackagent/api/judge/__init__.py
hackagent/api/judge/judge_create.py
hackagent/api/key/__init__.py
hackagent/api/key/key_create.py
hackagent/api/key/key_destroy.py
hackagent/api/key/key_list.py
hackagent/api/key/key_retrieve.py
hackagent/api/organization/__init__.py
hackagent/api/organization/organization_create.py
hackagent/api/organization/organization_destroy.py
hackagent/api/organization/organization_list.py
hackagent/api/organization/organization_me_retrieve.py
hackagent/api/organization/organization_partial_update.py
hackagent/api/organization/organization_retrieve.py
hackagent/api/organization/organization_update.py
hackagent/api/prompt/__init__.py
hackagent/api/prompt/prompt_create.py
hackagent/api/prompt/prompt_destroy.py
hackagent/api/prompt/prompt_list.py
hackagent/api/prompt/prompt_partial_update.py
hackagent/api/prompt/prompt_retrieve.py
hackagent/api/prompt/prompt_update.py
hackagent/api/result/__init__.py
hackagent/api/result/result_create.py
hackagent/api/result/result_destroy.py
hackagent-0.3.1.dist-info/METADATA
hackagent-0.3.1.dist-info/WHEEL
hackagent-0.3.1.dist-info/entry_points.txt
hackagent-0.3.1.dist-info/licenses/LICENSE
hackagent-0.3.1.dist-info/RECORD
