Metadata-Version: 2.4
Name: hackagent
Version: 0.3.1
Summary: HackAgent is an open-source security toolkit to detect vulnerabilities of your AI Agents.
Author-email: AI Security Lab <ais@ai4i.it>
License: Apache-2.0
License-File: LICENSE
Keywords: agents,ai,security,testing,vulnerabilities
Classifier: Development Status :: 4 - Beta
Classifier: Intended Audience :: Developers
Classifier: License :: OSI Approved :: Apache Software License
Classifier: Programming Language :: Python :: 3
Classifier: Programming Language :: Python :: 3.10
Classifier: Programming Language :: Python :: 3.11
Classifier: Programming Language :: Python :: 3.12
Requires-Python: >=3.10
Requires-Dist: click>=8.1.0
Requires-Dist: litellm>=1.69.2
Requires-Dist: openai>=1.0.0
Requires-Dist: pandas>=2.2.3
Requires-Dist: pydantic>=2.0
Requires-Dist: python-dotenv>=1.1.0
Requires-Dist: pyyaml>=6.0.0
Requires-Dist: requests>=2.31.0
Requires-Dist: rich>=14.0.0
Requires-Dist: textual>=1.0.0
